README.md
setup.cfg
setup.py
pushowl_utils/__init__.py
pushowl_utils.egg-info/PKG-INFO
pushowl_utils.egg-info/SOURCES.txt
pushowl_utils.egg-info/dependency_links.txt
pushowl_utils.egg-info/top_level.txt