Metadata-Version: 1.0
Name: pushowl-utils
Version: 0.0.1
Summary: Utils packages for PushOwl
Home-page: http://github.com/pushowl/pushowl_utils
Author: PushOwl
Author-email: info@pushowl.com
License: UNKNOWN
Keywords: pip,utils
Platform: UNKNOWN
